pseudo_builder.py
release_gitter.py
release_gitter-3.1.0.dist-info/METADATA
release_gitter-3.1.0.dist-info/WHEEL
release_gitter-3.1.0.dist-info/entry_points.txt
release_gitter-3.1.0.dist-info/licenses/LICENSE
release_gitter-3.1.0.dist-info/RECORD
