Metadata-Version: 2.4
Name: release-gitter
Version: 3.1.0
Summary: Easily download releases from sites like Github and Gitea
Project-URL: Homepage, https://git.iamthefij.com/iamthefij/release-gitter
Author-email: Ian Fijolek <iamthefij@gmail.com>
Maintainer-email: Ian Fijolek <iamthefij@gmail.com>
License-Expression: MIT
License-File: LICENSE
Classifier: License :: OSI Approved :: MIT License
Classifier: Operating System :: OS Independent
Classifier: Programming Language :: Python :: 3
Requires-Python: >=3.7
Requires-Dist: requests
Provides-Extra: builder
Requires-Dist: toml; extra == 'builder'
Requires-Dist: wheel; extra == 'builder'
